{
  "classname": null,
  "name": null,
  "animation": {
    "classname": null,
    "name": "AnimationManager",
    "actionlist": []
  },
  "dataScale": 1,
  "designHeight": 640,
  "designWidth": 960,
  "textures": [],
  "texturesPng": [
    "bg/stage-map-frame.png",
    "map_bg/stageselect_map_bg_1.jpg",
    "map_bg/map1.png",
    "maptitle_chapter/map-title-bg.png",
    "maptitle_chapter/maptitle-chapter1.png",
    "stageselect_difficulty_button_normal.png",
    "stageselect_difficulty_button_selected.png",
    "battlebg/detail_bg_2.png",
    "battlebg/backbtn.png",
    "battlebg/backbtn-disabled.png",
    "GUI/image.png",
    "battlebg/startbtn.png",
    "battlebg/startbtn-disabled.png",
    "stageselect_chapter_dot.png",
    "stageselect_chapter_cursor.png"
  ],
  "version": "1.5.0.0",
  "widgetTree": {
    "classname": "Panel",
    "name": null,
    "children": [
      {
        "classname": "Panel",
        "name": null,
        "children": [
          {
            "classname": "ImageView",
            "name": null,
            "children": [],
            "options": {
              "__type": "ImageViewSurrogate:#EditorCommon.JsonModel.Component.GUI",
              "classname": "ImageView",
              "name": "Image_bg1",
              "ZOrder": 1,
              "actiontag": 3773844,
              "anchorPointX": 0.5,
              "anchorPointY": 0.5,
              "classType": "CocoStudio.EngineAdapterWrap.CSImageView",
              "colorB": 255,
              "colorG": 255,
              "colorR": 255,
              "customProperty": "",
              "flipX": false,
              "flipY": false,
              "height": 507,
              "ignoreSize": true,
              "layoutParameter": null,
              "opacity": 255,
              "positionPercentX": 0.5,
              "positionPercentY": 0.4990138,
              "positionType": 0,
              "rotation": 0,
              "scaleX": 1,
              "scaleY": 1,
              "sizePercentX": 1,
              "sizePercentY": 1,
              "sizeType": 0,
              "tag": 7,
              "touchAble": false,
              "useMergedTexture": false,
              "visible": true,
              "width": 936,
              "x": 468,
              "y": 253,
              "capInsetsHeight": 1,
              "capInsetsWidth": 1,
              "capInsetsX": 0,
              "capInsetsY": 0,
              "fileName": null,
              "fileNameData": {
                "path": "bg/stage-map-frame.png",
                "plistFile": "",
                "resourceType": 0
              },
              "scale9Enable": false,
              "scale9Height": 507,
              "scale9Width": 936
            }
          },
          {
            "classname": "PageView",
            "name": null,
            "children": [
              {
                "classname": "Panel",
                "name": null,
                "children": [
                  {
                    "classname": "ImageView",
                    "name": null,
                    "children": [],
                    "options": {
                      "__type": "ImageViewSurrogate:#EditorCommon.JsonModel.Component.GUI",
                      "classname": "ImageView",
                      "name": "Image_Page",
                      "ZOrder": 0,
                      "actiontag": 10202947,
                      "anchorPointX": 0.5,
                      "anchorPointY": 0.5,
                      "classType": "CocoStudio.EngineAdapterWrap.CSImageView",
                      "colorB": 255,
                      "colorG": 255,
                      "colorR": 255,
                      "customProperty": "",
                      "flipX": false,
                      "flipY": false,
                      "height": 254,
                      "ignoreSize": true,
                      "layoutParameter": null,
                      "opacity": 255,
                      "positionPercentX": 0.5,
                      "positionPercentY": 0.503937,
                      "positionType": 0,
                      "rotation": 0,
                      "scaleX": 1,
                      "scaleY": 1,
                      "sizePercentX": 1,
                      "sizePercentY": 1,
                      "sizeType": 0,
                      "tag": 13,
                      "touchAble": false,
                      "useMergedTexture": false,
                      "visible": true,
                      "width": 468,
                      "x": 234,
                      "y": 128,
                      "capInsetsHeight": 1,
                      "capInsetsWidth": 1,
                      "capInsetsX": 0,
                      "capInsetsY": 0,
                      "fileName": null,
                      "fileNameData": {
                        "path": "map_bg/map1.png",
                        "plistFile": "",
                        "resourceType": 0
                      },
                      "scale9Enable": false,
                      "scale9Height": 254,
                      "scale9Width": 468
                    }
                  }
                ],
                "options": {
                  "__type": "PanelSurrogate:#EditorCommon.JsonModel.Component.GUI",
                  "classname": "Panel",
                  "name": "Panel_Page1",
                  "ZOrder": 0,
                  "actiontag": 6950619,
                  "anchorPointX": 0,
                  "anchorPointY": 0,
                  "classType": "CocoStudio.EngineAdapterWrap.CSPanel",
                  "colorB": 255,
                  "colorG": 255,
                  "colorR": 255,
                  "customProperty": "",
                  "flipX": false,
                  "flipY": false,
                  "height": 254,
                  "ignoreSize": false,
                  "layoutParameter": null,
                  "opacity": 255,
                  "positionPercentX": 0,
                  "positionPercentY": 0,
                  "positionType": 0,
                  "rotation": 0,
                  "scaleX": 1,
                  "scaleY": 1,
                  "sizePercentX": 1,
                  "sizePercentY": 1,
                  "sizeType": 0,
                  "tag": 10,
                  "touchAble": true,
                  "useMergedTexture": false,
                  "visible": true,
                  "width": 468,
                  "x": 0,
                  "y": 0,
                  "adaptScreen": false,
                  "backGroundImage": null,
                  "backGroundImageData": {
                    "path": "map_bg/stageselect_map_bg_1.jpg",
                    "plistFile": "",
                    "resourceType": 0
                  },
                  "backGroundScale9Enable": false,
                  "bgColorB": 255,
                  "bgColorG": 200,
                  "bgColorOpacity": 100,
                  "bgColorR": 150,
                  "bgEndColorB": 255,
                  "bgEndColorG": 200,
                  "bgEndColorR": 150,
                  "bgStartColorB": 255,
                  "bgStartColorG": 255,
                  "bgStartColorR": 255,
                  "capInsetsHeight": 1,
                  "capInsetsWidth": 1,
                  "capInsetsX": 0,
                  "capInsetsY": 0,
                  "clipAble": false,
                  "colorType": 1,
                  "layoutType": 0,
                  "vectorX": 0,
                  "vectorY": -0.5
                }
              }
            ],
            "options": {
              "__type": "PageViewSurrogate:#EditorCommon.JsonModel.Component.GUI",
              "classname": "PageView",
              "name": "PageView",
              "ZOrder": 0,
              "actiontag": 28038651,
              "anchorPointX": 0,
              "anchorPointY": 0,
              "classType": "CocoStudio.EngineAdapterWrap.CSPageView",
              "colorB": 255,
              "colorG": 255,
              "colorR": 255,
              "customProperty": "",
              "flipX": false,
              "flipY": false,
              "height": 254,
              "ignoreSize": false,
              "layoutParameter": null,
              "opacity": 255,
              "positionPercentX": 0.011752137,
              "positionPercentY": 0.0276134126,
              "positionType": 0,
              "rotation": 0,
              "scaleX": 1.95275462,
              "scaleY": 1.89501429,
              "sizePercentX": 0.5,
              "sizePercentY": 0.5009862,
              "sizeType": 0,
              "tag": 8,
              "touchAble": true,
              "useMergedTexture": false,
              "visible": true,
              "width": 468,
              "x": 11,
              "y": 14,
              "backGroundImage": null,
              "backGroundImageData": null,
              "backGroundScale9Enable": false,
              "bgColorB": 100,
              "bgColorG": 150,
              "bgColorOpacity": 100,
              "bgColorR": 150,
              "bgEndColorB": 100,
              "bgEndColorG": 150,
              "bgEndColorR": 255,
              "bgStartColorB": 255,
              "bgStartColorG": 255,
              "bgStartColorR": 255,
              "capInsetsHeight": 1,
              "capInsetsWidth": 1,
              "capInsetsX": 0,
              "capInsetsY": 0,
              "clipAble": true,
              "colorType": 1,
              "editorClipAble": false,
              "vectorX": 0,
              "vectorY": -0.5
            }
          },
          {
            "classname": "Panel",
            "name": null,
            "children": [
              {
                "classname": "ImageView",
                "name": null,
                "children": [
                  {
                    "classname": "ImageView",
                    "name": null,
                    "children": [],
                    "options": {
                      "__type": "ImageViewSurrogate:#EditorCommon.JsonModel.Component.GUI",
                      "classname": "ImageView",
                      "name": "map-tiltle-image",
                      "ZOrder": 0,
                      "actiontag": 44039998,
                      "anchorPointX": 0.5,
                      "anchorPointY": 0.5,
                      "classType": "CocoStudio.EngineAdapterWrap.CSImageView",
                      "colorB": 255,
                      "colorG": 255,
                      "colorR": 255,
                      "customProperty": "",
                      "flipX": false,
                      "flipY": false,
                      "height": 103,
                      "ignoreSize": true,
                      "layoutParameter": null,
                      "opacity": 255,
                      "positionPercentX": 0,
                      "positionPercentY": 0,
                      "positionType": 0,
                      "rotation": 0,
                      "scaleX": 1,
                      "scaleY": 1,
                      "sizePercentX": 1,
                      "sizePercentY": 1,
                      "sizeType": 0,
                      "tag": 68,
                      "touchAble": false,
                      "useMergedTexture": false,
                      "visible": true,
                      "width": 491,
                      "x": 0,
                      "y": 0,
                      "capInsetsHeight": 1,
                      "capInsetsWidth": 1,
                      "capInsetsX": 0,
                      "capInsetsY": 0,
                      "fileName": null,
                      "fileNameData": {
                        "path": "maptitle_chapter/maptitle-chapter1.png",
                        "plistFile": "",
                        "resourceType": 0
                      },
                      "scale9Enable": false,
                      "scale9Height": 103,
                      "scale9Width": 491
                    }
                  }
                ],
                "options": {
                  "__type": "ImageViewSurrogate:#EditorCommon.JsonModel.Component.GUI",
                  "classname": "ImageView",
                  "name": "map-title-bg",
                  "ZOrder": 2,
                  "actiontag": 63481374,
                  "anchorPointX": 0.5,
                  "anchorPointY": 0.5,
                  "classType": "CocoStudio.EngineAdapterWrap.CSImageView",
                  "colorB": 255,
                  "colorG": 255,
                  "colorR": 255,
                  "customProperty": "",
                  "flipX": false,
                  "flipY": false,
                  "height": 103,
                  "ignoreSize": true,
                  "layoutParameter": null,
                  "opacity": 255,
                  "positionPercentX": 0.336666673,
                  "positionPercentY": 0.5,
                  "positionType": 0,
                  "rotation": 0,
                  "scaleX": 1,
                  "scaleY": 1,
                  "sizePercentX": 0.545555532,
                  "sizePercentY": 1.03,
                  "sizeType": 0,
                  "tag": 66,
                  "touchAble": false,
                  "useMergedTexture": false,
                  "visible": true,
                  "width": 491,
                  "x": 303,
                  "y": 50,
                  "capInsetsHeight": 1,
                  "capInsetsWidth": 1,
                  "capInsetsX": 0,
                  "capInsetsY": 0,
                  "fileName": null,
                  "fileNameData": {
                    "path": "maptitle_chapter/map-title-bg.png",
                    "plistFile": "",
                    "resourceType": 0
                  },
                  "scale9Enable": false,
                  "scale9Height": 103,
                  "scale9Width": 491
                }
              },
              {
                "classname": "CheckBox",
                "name": null,
                "children": [
                  {
                    "classname": "Label",
                    "name": null,
                    "children": [],
                    "options": {
                      "__type": "LabelSurrogate:#EditorCommon.JsonModel.Component.GUI",
                      "classname": "Label",
                      "name": "Label_btnname",
                      "ZOrder": 0,
                      "actiontag": 28067877,
                      "anchorPointX": 0.5,
                      "anchorPointY": 0.5,
                      "classType": "CocoStudio.EngineAdapterWrap.CSLabel",
                      "colorB": 14,
                      "colorG": 175,
                      "colorR": 212,
                      "customProperty": "",
                      "flipX": false,
                      "flipY": false,
                      "height": 38,
                      "ignoreSize": true,
                      "layoutParameter": null,
                      "opacity": 255,
                      "positionPercentX": 0,
                      "positionPercentY": 0.0298507456,
                      "positionType": 0,
                      "rotation": 0,
                      "scaleX": 1,
                      "scaleY": 1,
                      "sizePercentX": 0.5576923,
                      "sizePercentY": 0.5671642,
                      "sizeType": 0,
                      "tag": 73,
                      "touchAble": false,
                      "useMergedTexture": false,
                      "visible": true,
                      "width": 58,
                      "x": 0,
                      "y": 2,
                      "areaHeight": 0,
                      "areaWidth": 0,
                      "fontFile": null,
                      "fontName": "微软雅黑",
                      "fontSize": 29,
                      "hAlignment": 0,
                      "text": "普通",
                      "touchScaleEnable": false,
                      "vAlignment": 0
                    }
                  }
                ],
                "options": {
                  "__type": "CheckBoxSurrogate:#EditorCommon.JsonModel.Component.GUI",
                  "classname": "CheckBox",
                  "name": "sgateselect_1",
                  "ZOrder": 2,
                  "actiontag": 64537842,
                  "anchorPointX": 0.5,
                  "anchorPointY": 0.5,
                  "classType": "CocoStudio.EngineAdapterWrap.CSCheckBox",
                  "colorB": 255,
                  "colorG": 255,
                  "colorR": 255,
                  "customProperty": "",
                  "flipX": false,
                  "flipY": false,
                  "height": 67,
                  "ignoreSize": true,
                  "layoutParameter": null,
                  "opacity": 255,
                  "positionPercentX": 0.73,
                  "positionPercentY": 0.55,
                  "positionType": 0,
                  "rotation": 0,
                  "scaleX": 1,
                  "scaleY": 1,
                  "sizePercentX": 0.115555555,
                  "sizePercentY": 0.67,
                  "sizeType": 0,
                  "tag": 72,
                  "touchAble": true,
                  "useMergedTexture": false,
                  "visible": true,
                  "width": 104,
                  "x": 657,
                  "y": 55,
                  "backGroundBox": null,
                  "backGroundBoxData": {
                    "path": "stageselect_difficulty_button_normal.png",
                    "plistFile": "",
                    "resourceType": 0
                  },
                  "backGroundBoxDisabled": null,
                  "backGroundBoxDisabledData": {
                    "path": null,
                    "plistFile": null,
                    "resourceType": 0
                  },
                  "backGroundBoxSelected": null,
                  "backGroundBoxSelectedData": {
                    "path": "stageselect_difficulty_button_selected.png",
                    "plistFile": "",
                    "resourceType": 0
                  },
                  "frontCross": null,
                  "frontCrossData": {
                    "path": "stageselect_difficulty_button_selected.png",
                    "plistFile": "",
                    "resourceType": 0
                  },
                  "frontCrossDisabled": null,
                  "frontCrossDisabledData": {
                    "path": null,
                    "plistFile": null,
                    "resourceType": 0
                  },
                  "selectedState": false
                }
              }
            ],
            "options": {
              "__type": "PanelSurrogate:#EditorCommon.JsonModel.Component.GUI",
              "classname": "Panel",
              "name": "Panel_Title",
              "ZOrder": 2,
              "actiontag": 29515756,
              "anchorPointX": 0,
              "anchorPointY": 0,
              "classType": "CocoStudio.EngineAdapterWrap.CSPanel",
              "colorB": 255,
              "colorG": 255,
              "colorR": 255,
              "customProperty": "",
              "flipX": false,
              "flipY": false,
              "height": 100,
              "ignoreSize": false,
              "layoutParameter": null,
              "opacity": 255,
              "positionPercentX": 0.0181623939,
              "positionPercentY": 0.8382643,
              "positionType": 0,
              "rotation": 0,
              "scaleX": 1,
              "scaleY": 1,
              "sizePercentX": 0.961538434,
              "sizePercentY": 0.197238654,
              "sizeType": 0,
              "tag": 99,
              "touchAble": true,
              "useMergedTexture": false,
              "visible": true,
              "width": 900,
              "x": 17,
              "y": 425,
              "adaptScreen": false,
              "backGroundImage": null,
              "backGroundImageData": null,
              "backGroundScale9Enable": false,
              "bgColorB": 255,
              "bgColorG": 200,
              "bgColorOpacity": 0,
              "bgColorR": 150,
              "bgEndColorB": 255,
              "bgEndColorG": 200,
              "bgEndColorR": 150,
              "bgStartColorB": 255,
              "bgStartColorG": 255,
              "bgStartColorR": 255,
              "capInsetsHeight": 1,
              "capInsetsWidth": 1,
              "capInsetsX": 0,
              "capInsetsY": 0,
              "clipAble": false,
              "colorType": 1,
              "layoutType": 0,
              "vectorX": 0,
              "vectorY": -0.5
            }
          },
          {
            "classname": "Panel",
            "name": null,
            "children": [
              {
                "classname": "Button",
                "name": null,
                "children": [],
                "options": {
                  "__type": "ButtonSurrogate:#EditorCommon.JsonModel.Component.GUI",
                  "classname": "Button",
                  "name": "startBg_back",
                  "ZOrder": 2,
                  "actiontag": 23519558,
                  "anchorPointX": 0.5,
                  "anchorPointY": 0.5,
                  "classType": "CocoStudio.EngineAdapterWrap.CSButton",
                  "colorB": 255,
                  "colorG": 255,
                  "colorR": 255,
                  "customProperty": "",
                  "flipX": false,
                  "flipY": false,
                  "height": 75,
                  "ignoreSize": true,
                  "layoutParameter": null,
                  "opacity": 255,
                  "positionPercentX": 0.110042736,
                  "positionPercentY": 0.875739634,
                  "positionType": 0,
                  "rotation": 0,
                  "scaleX": 1,
                  "scaleY": 1,
                  "sizePercentX": 0.07905983,
                  "sizePercentY": 0.147929,
                  "sizeType": 0,
                  "tag": 125,
                  "touchAble": true,
                  "useMergedTexture": false,
                  "visible": true,
                  "width": 74,
                  "x": 103,
                  "y": 444,
                  "capInsetsHeight": 1,
                  "capInsetsWidth": 1,
                  "capInsetsX": 0,
                  "capInsetsY": 0,
                  "disabled": null,
                  "disabledData": {
                    "path": "battlebg/backbtn-disabled.png",
                    "plistFile": "",
                    "resourceType": 0
                  },
                  "fontName": "微软雅黑",
                  "fontSize": 14,
                  "fontType": 0,
                  "normal": null,
                  "normalData": {
                    "path": "battlebg/backbtn.png",
                    "plistFile": "",
                    "resourceType": 0
                  },
                  "pressed": null,
                  "pressedData": {
                    "path": null,
                    "plistFile": null,
                    "resourceType": 0
                  },
                  "scale9Enable": false,
                  "scale9Height": 75,
                  "scale9Width": 74,
                  "text": "",
                  "textColorB": 255,
                  "textColorG": 255,
                  "textColorR": 255
                }
              },
              {
                "classname": "Label",
                "name": null,
                "children": [],
                "options": {
                  "__type": "LabelSurrogate:#EditorCommon.JsonModel.Component.GUI",
                  "classname": "Label",
                  "name": "Labe_stagetitle",
                  "ZOrder": 0,
                  "actiontag": 9293580,
                  "anchorPointX": 0.5,
                  "anchorPointY": 0.5,
                  "classType": "CocoStudio.EngineAdapterWrap.CSLabel",
                  "colorB": 255,
                  "colorG": 255,
                  "colorR": 255,
                  "customProperty": "",
                  "flipX": false,
                  "flipY": false,
                  "height": 46,
                  "ignoreSize": true,
                  "layoutParameter": null,
                  "opacity": 255,
                  "positionPercentX": 0.5,
                  "positionPercentY": 0.90729785,
                  "positionType": 0,
                  "rotation": 0,
                  "scaleX": 1,
                  "scaleY": 1,
                  "sizePercentX": 0.180555552,
                  "sizePercentY": 0.09072978,
                  "sizeType": 0,
                  "tag": 126,
                  "touchAble": false,
                  "useMergedTexture": false,
                  "visible": true,
                  "width": 169,
                  "x": 468,
                  "y": 460,
                  "areaHeight": 0,
                  "areaWidth": 0,
                  "fontFile": null,
                  "fontName": "微软雅黑",
                  "fontSize": 35,
                  "hAlignment": 0,
                  "text": "Text Label",
                  "touchScaleEnable": false,
                  "vAlignment": 0
                }
              },
              {
                "classname": "Panel",
                "name": null,
                "children": [
                  {
                    "classname": "ImageView",
                    "name": null,
                    "children": [],
                    "options": {
                      "__type": "ImageViewSurrogate:#EditorCommon.JsonModel.Component.GUI",
                      "classname": "ImageView",
                      "name": "Image_stageDes",
                      "ZOrder": 0,
                      "actiontag": 30645897,
                      "anchorPointX": 0.5,
                      "anchorPointY": 0.5,
                      "classType": "CocoStudio.EngineAdapterWrap.CSImageView",
                      "colorB": 255,
                      "colorG": 255,
                      "colorR": 255,
                      "customProperty": "",
                      "flipX": false,
                      "flipY": false,
                      "height": 80,
                      "ignoreSize": true,
                      "layoutParameter": null,
                      "opacity": 255,
                      "positionPercentX": 0.08852459,
                      "positionPercentY": 0.48,
                      "positionType": 0,
                      "rotation": 0,
                      "scaleX": 1,
                      "scaleY": 1,
                      "sizePercentX": 0.131147534,
                      "sizePercentY": 0.8,
                      "sizeType": 0,
                      "tag": 137,
                      "touchAble": false,
                      "useMergedTexture": false,
                      "visible": true,
                      "width": 80,
                      "x": 54,
                      "y": 48,
                      "capInsetsHeight": 1,
                      "capInsetsWidth": 1,
                      "capInsetsX": 0,
                      "capInsetsY": 0,
                      "fileName": null,
                      "fileNameData": {
                        "path": "GUI/image.png",
                        "plistFile": "",
                        "resourceType": 0
                      },
                      "scale9Enable": false,
                      "scale9Height": 80,
                      "scale9Width": 80
                    }
                  },
                  {
                    "classname": "Label",
                    "name": null,
                    "children": [],
                    "options": {
                      "__type": "LabelSurrogate:#EditorCommon.JsonModel.Component.GUI",
                      "classname": "Label",
                      "name": "Label_stageDes",
                      "ZOrder": 5,
                      "actiontag": 66036767,
                      "anchorPointX": 0,
                      "anchorPointY": 1,
                      "classType": "CocoStudio.EngineAdapterWrap.CSLabel",
                      "colorB": 255,
                      "colorG": 255,
                      "colorR": 255,
                      "customProperty": "",
                      "flipX": false,
                      "flipY": false,
                      "height": 32,
                      "ignoreSize": true,
                      "layoutParameter": null,
                      "opacity": 255,
                      "positionPercentX": 0.177049175,
                      "positionPercentY": 0.84,
                      "positionType": 0,
                      "rotation": 0,
                      "scaleX": 1,
                      "scaleY": 1,
                      "sizePercentX": 0.163934425,
                      "sizePercentY": 0.32,
                      "sizeType": 0,
                      "tag": 138,
                      "touchAble": false,
                      "useMergedTexture": false,
                      "visible": true,
                      "width": 100,
                      "x": 108,
                      "y": 84,
                      "areaHeight": 0,
                      "areaWidth": 0,
                      "fontFile": null,
                      "fontName": "微软雅黑",
                      "fontSize": 25,
                      "hAlignment": 0,
                      "text": "黄金之乱",
                      "touchScaleEnable": false,
                      "vAlignment": 0
                    }
                  }
                ],
                "options": {
                  "__type": "PanelSurrogate:#EditorCommon.JsonModel.Component.GUI",
                  "classname": "Panel",
                  "name": "Panel_stageDes",
                  "ZOrder": 0,
                  "actiontag": 31271587,
                  "anchorPointX": 0,
                  "anchorPointY": 0,
                  "classType": "CocoStudio.EngineAdapterWrap.CSPanel",
                  "colorB": 255,
                  "colorG": 255,
                  "colorR": 255,
                  "customProperty": "",
                  "flipX": false,
                  "flipY": false,
                  "height": 100,
                  "ignoreSize": false,
                  "layoutParameter": null,
                  "opacity": 255,
                  "positionPercentX": 0.168803424,
                  "positionPercentY": 0.654832363,
                  "positionType": 0,
                  "rotation": 0,
                  "scaleX": 1,
                  "scaleY": 1,
                  "sizePercentX": 0.6517094,
                  "sizePercentY": 0.197238654,
                  "sizeType": 0,
                  "tag": 127,
                  "touchAble": true,
                  "useMergedTexture": false,
                  "visible": true,
                  "width": 610,
                  "x": 158,
                  "y": 332,
                  "adaptScreen": false,
                  "backGroundImage": null,
                  "backGroundImageData": null,
                  "backGroundScale9Enable": false,
                  "bgColorB": 0,
                  "bgColorG": 0,
                  "bgColorOpacity": 100,
                  "bgColorR": 0,
                  "bgEndColorB": 255,
                  "bgEndColorG": 200,
                  "bgEndColorR": 150,
                  "bgStartColorB": 255,
                  "bgStartColorG": 255,
                  "bgStartColorR": 255,
                  "capInsetsHeight": 1,
                  "capInsetsWidth": 1,
                  "capInsetsX": 0,
                  "capInsetsY": 0,
                  "clipAble": false,
                  "colorType": 1,
                  "layoutType": 0,
                  "vectorX": 0,
                  "vectorY": -0.5
                }
              },
              {
                "classname": "Label",
                "name": null,
                "children": [],
                "options": {
                  "__type": "LabelSurrogate:#EditorCommon.JsonModel.Component.GUI",
                  "classname": "Label",
                  "name": "Labe_junlingxiaohaoText",
                  "ZOrder": 0,
                  "actiontag": 34450862,
                  "anchorPointX": 0.5,
                  "anchorPointY": 0.5,
                  "classType": "CocoStudio.EngineAdapterWrap.CSLabel",
                  "colorB": 255,
                  "colorG": 255,
                  "colorR": 255,
                  "customProperty": "",
                  "flipX": false,
                  "flipY": false,
                  "height": 35,
                  "ignoreSize": true,
                  "layoutParameter": null,
                  "opacity": 255,
                  "positionPercentX": 0.136752144,
                  "positionPercentY": 0.5739645,
                  "positionType": 0,
                  "rotation": 0,
                  "scaleX": 1,
                  "scaleY": 1,
                  "sizePercentX": 0.1388889,
                  "sizePercentY": 0.06903353,
                  "sizeType": 0,
                  "tag": 128,
                  "touchAble": false,
                  "useMergedTexture": false,
                  "visible": true,
                  "width": 130,
                  "x": 128,
                  "y": 291,
                  "areaHeight": 0,
                  "areaWidth": 0,
                  "fontFile": null,
                  "fontName": "微软雅黑",
                  "fontSize": 26,
                  "hAlignment": 0,
                  "text": "军令消耗：",
                  "touchScaleEnable": false,
                  "vAlignment": 0
                }
              },
              {
                "classname": "Label",
                "name": null,
                "children": [],
                "options": {
                  "__type": "LabelSurrogate:#EditorCommon.JsonModel.Component.GUI",
                  "classname": "Label",
                  "name": "Labe_junlingxiaohao",
                  "ZOrder": 0,
                  "actiontag": 47901489,
                  "anchorPointX": 0,
                  "anchorPointY": 1,
                  "classType": "CocoStudio.EngineAdapterWrap.CSLabel",
                  "colorB": 255,
                  "colorG": 255,
                  "colorR": 255,
                  "customProperty": "",
                  "flipX": false,
                  "flipY": false,
                  "height": 35,
                  "ignoreSize": true,
                  "layoutParameter": null,
                  "opacity": 255,
                  "positionPercentX": 0.20726496,
                  "positionPercentY": 0.60749507,
                  "positionType": 0,
                  "rotation": 0,
                  "scaleX": 1,
                  "scaleY": 1,
                  "sizePercentX": 0.0160256419,
                  "sizePercentY": 0.06903353,
                  "sizeType": 0,
                  "tag": 129,
                  "touchAble": false,
                  "useMergedTexture": false,
                  "visible": true,
                  "width": 15,
                  "x": 194,
                  "y": 308,
                  "areaHeight": 0,
                  "areaWidth": 0,
                  "fontFile": null,
                  "fontName": "微软雅黑",
                  "fontSize": 26,
                  "hAlignment": 0,
                  "text": "0",
                  "touchScaleEnable": false,
                  "vAlignment": 0
                }
              },
              {
                "classname": "Label",
                "name": null,
                "children": [],
                "options": {
                  "__type": "LabelSurrogate:#EditorCommon.JsonModel.Component.GUI",
                  "classname": "Label",
                  "name": "Labe_jinrixishuText",
                  "ZOrder": 0,
                  "actiontag": 16123342,
                  "anchorPointX": 0.5,
                  "anchorPointY": 0.5,
                  "classType": "CocoStudio.EngineAdapterWrap.CSLabel",
                  "colorB": 255,
                  "colorG": 255,
                  "colorR": 255,
                  "customProperty": "",
                  "flipX": false,
                  "flipY": false,
                  "height": 35,
                  "ignoreSize": true,
                  "layoutParameter": null,
                  "opacity": 255,
                  "positionPercentX": 0.3707265,
                  "positionPercentY": 0.575936854,
                  "positionType": 0,
                  "rotation": 0,
                  "scaleX": 1,
                  "scaleY": 1,
                  "sizePercentX": 0.1388889,
                  "sizePercentY": 0.06903353,
                  "sizeType": 0,
                  "tag": 130,
                  "touchAble": false,
                  "useMergedTexture": false,
                  "visible": true,
                  "width": 130,
                  "x": 347,
                  "y": 292,
                  "areaHeight": 0,
                  "areaWidth": 0,
                  "fontFile": null,
                  "fontName": "微软雅黑",
                  "fontSize": 26,
                  "hAlignment": 0,
                  "text": "今日次数：",
                  "touchScaleEnable": false,
                  "vAlignment": 0
                }
              },
              {
                "classname": "Label",
                "name": null,
                "children": [],
                "options": {
                  "__type": "LabelSurrogate:#EditorCommon.JsonModel.Component.GUI",
                  "classname": "Label",
                  "name": "Labe_jinrixishu",
                  "ZOrder": 0,
                  "actiontag": 9164568,
                  "anchorPointX": 0,
                  "anchorPointY": 0,
                  "classType": "CocoStudio.EngineAdapterWrap.CSLabel",
                  "colorB": 255,
                  "colorG": 255,
                  "colorR": 255,
                  "customProperty": "",
                  "flipX": false,
                  "flipY": false,
                  "height": 35,
                  "ignoreSize": true,
                  "layoutParameter": null,
                  "opacity": 255,
                  "positionPercentX": 0.441239327,
                  "positionPercentY": 0.540433943,
                  "positionType": 0,
                  "rotation": 0,
                  "scaleX": 1,
                  "scaleY": 1,
                  "sizePercentX": 0.04380342,
                  "sizePercentY": 0.06903353,
                  "sizeType": 0,
                  "tag": 132,
                  "touchAble": false,
                  "useMergedTexture": false,
                  "visible": true,
                  "width": 41,
                  "x": 413,
                  "y": 274,
                  "areaHeight": 0,
                  "areaWidth": 0,
                  "fontFile": null,
                  "fontName": "微软雅黑",
                  "fontSize": 26,
                  "hAlignment": 0,
                  "text": "0/0",
                  "touchScaleEnable": false,
                  "vAlignment": 0
                }
              },
              {
                "classname": "Label",
                "name": null,
                "children": [
                  {
                    "classname": "ImageView",
                    "name": null,
                    "children": [],
                    "options": {
                      "__type": "ImageViewSurrogate:#EditorCommon.JsonModel.Component.GUI",
                      "classname": "ImageView",
                      "name": "Image_formation",
                      "ZOrder": 0,
                      "actiontag": 825788,
                      "anchorPointX": 0.5,
                      "anchorPointY": 0.5,
                      "classType": "CocoStudio.EngineAdapterWrap.CSImageView",
                      "colorB": 255,
                      "colorG": 255,
                      "colorR": 255,
                      "customProperty": "",
                      "flipX": false,
                      "flipY": false,
                      "height": 80,
                      "ignoreSize": true,
                      "layoutParameter": null,
                      "opacity": 255,
                      "positionPercentX": 0.953846157,
                      "positionPercentY": 0.0571428575,
                      "positionType": 0,
                      "rotation": 0,
                      "scaleX": 1,
                      "scaleY": 1,
                      "sizePercentX": 0.615384638,
                      "sizePercentY": 2.28571439,
                      "sizeType": 0,
                      "tag": 139,
                      "touchAble": false,
                      "useMergedTexture": false,
                      "visible": false,
                      "width": 80,
                      "x": 124,
                      "y": 2,
                      "capInsetsHeight": 1,
                      "capInsetsWidth": 1,
                      "capInsetsX": 0,
                      "capInsetsY": 0,
                      "fileName": null,
                      "fileNameData": {
                        "path": "GUI/image.png",
                        "plistFile": "",
                        "resourceType": 0
                      },
                      "scale9Enable": false,
                      "scale9Height": 80,
                      "scale9Width": 80
                    }
                  }
                ],
                "options": {
                  "__type": "LabelSurrogate:#EditorCommon.JsonModel.Component.GUI",
                  "classname": "Label",
                  "name": "Label_formationText",
                  "ZOrder": 0,
                  "actiontag": 6273757,
                  "anchorPointX": 0.5,
                  "anchorPointY": 0.5,
                  "classType": "CocoStudio.EngineAdapterWrap.CSLabel",
                  "colorB": 255,
                  "colorG": 255,
                  "colorR": 255,
                  "customProperty": "",
                  "flipX": false,
                  "flipY": false,
                  "height": 35,
                  "ignoreSize": true,
                  "layoutParameter": null,
                  "opacity": 255,
                  "positionPercentX": 0.136752144,
                  "positionPercentY": 0.445759356,
                  "positionType": 0,
                  "rotation": 0,
                  "scaleX": 1,
                  "scaleY": 1,
                  "sizePercentX": 0.1388889,
                  "sizePercentY": 0.06903353,
                  "sizeType": 0,
                  "tag": 133,
                  "touchAble": false,
                  "useMergedTexture": false,
                  "visible": true,
                  "width": 130,
                  "x": 128,
                  "y": 226,
                  "areaHeight": 0,
                  "areaWidth": 0,
                  "fontFile": null,
                  "fontName": "微软雅黑",
                  "fontSize": 26,
                  "hAlignment": 0,
                  "text": "敌方阵形：",
                  "touchScaleEnable": false,
                  "vAlignment": 0
                }
              },
              {
                "classname": "Label",
                "name": null,
                "children": [
                  {
                    "classname": "ImageView",
                    "name": null,
                    "children": [],
                    "options": {
                      "__type": "ImageViewSurrogate:#EditorCommon.JsonModel.Component.GUI",
                      "classname": "ImageView",
                      "name": "Image_hero1",
                      "ZOrder": 0,
                      "actiontag": 48605214,
                      "anchorPointX": 0.5,
                      "anchorPointY": 0.5,
                      "classType": "CocoStudio.EngineAdapterWrap.CSImageView",
                      "colorB": 255,
                      "colorG": 255,
                      "colorR": 255,
                      "customProperty": "",
                      "flipX": false,
                      "flipY": false,
                      "height": 80,
                      "ignoreSize": true,
                      "layoutParameter": null,
                      "opacity": 255,
                      "positionPercentX": 0.953846157,
                      "positionPercentY": -0.08571429,
                      "positionType": 0,
                      "rotation": 0,
                      "scaleX": 1,
                      "scaleY": 1,
                      "sizePercentX": 0.615384638,
                      "sizePercentY": 2.28571439,
                      "sizeType": 0,
                      "tag": 140,
                      "touchAble": false,
                      "useMergedTexture": false,
                      "visible": false,
                      "width": 80,
                      "x": 124,
                      "y": -3,
                      "capInsetsHeight": 1,
                      "capInsetsWidth": 1,
                      "capInsetsX": 0,
                      "capInsetsY": 0,
                      "fileName": null,
                      "fileNameData": {
                        "path": "GUI/image.png",
                        "plistFile": "",
                        "resourceType": 0
                      },
                      "scale9Enable": false,
                      "scale9Height": 80,
                      "scale9Width": 80
                    }
                  },
                  {
                    "classname": "ImageView",
                    "name": null,
                    "children": [],
                    "options": {
                      "__type": "ImageViewSurrogate:#EditorCommon.JsonModel.Component.GUI",
                      "classname": "ImageView",
                      "name": "Image_hero2",
                      "ZOrder": 0,
                      "actiontag": 21008427,
                      "anchorPointX": 0.5,
                      "anchorPointY": 0.5,
                      "classType": "CocoStudio.EngineAdapterWrap.CSImageView",
                      "colorB": 255,
                      "colorG": 255,
                      "colorR": 255,
                      "customProperty": "",
                      "flipX": false,
                      "flipY": false,
                      "height": 80,
                      "ignoreSize": true,
                      "layoutParameter": null,
                      "opacity": 255,
                      "positionPercentX": 1.60769236,
                      "positionPercentY": -0.08571429,
                      "positionType": 0,
                      "rotation": 0,
                      "scaleX": 1,
                      "scaleY": 1,
                      "sizePercentX": 0.615384638,
                      "sizePercentY": 2.28571439,
                      "sizeType": 0,
                      "tag": 142,
                      "touchAble": false,
                      "useMergedTexture": false,
                      "visible": false,
                      "width": 80,
                      "x": 209,
                      "y": -3,
                      "capInsetsHeight": 1,
                      "capInsetsWidth": 1,
                      "capInsetsX": 0,
                      "capInsetsY": 0,
                      "fileName": null,
                      "fileNameData": {
                        "path": "GUI/image.png",
                        "plistFile": "",
                        "resourceType": 0
                      },
                      "scale9Enable": false,
                      "scale9Height": 80,
                      "scale9Width": 80
                    }
                  },
                  {
                    "classname": "ImageView",
                    "name": null,
                    "children": [],
                    "options": {
                      "__type": "ImageViewSurrogate:#EditorCommon.JsonModel.Component.GUI",
                      "classname": "ImageView",
                      "name": "Image_hero3",
                      "ZOrder": 0,
                      "actiontag": 22466403,
                      "anchorPointX": 0.5,
                      "anchorPointY": 0.5,
                      "classType": "CocoStudio.EngineAdapterWrap.CSImageView",
                      "colorB": 255,
                      "colorG": 255,
                      "colorR": 255,
                      "customProperty": "",
                      "flipX": false,
                      "flipY": false,
                      "height": 80,
                      "ignoreSize": true,
                      "layoutParameter": null,
                      "opacity": 255,
                      "positionPercentX": 2.26153851,
                      "positionPercentY": -0.08571429,
                      "positionType": 0,
                      "rotation": 0,
                      "scaleX": 1,
                      "scaleY": 1,
                      "sizePercentX": 0.615384638,
                      "sizePercentY": 2.28571439,
                      "sizeType": 0,
                      "tag": 143,
                      "touchAble": false,
                      "useMergedTexture": false,
                      "visible": false,
                      "width": 80,
                      "x": 294,
                      "y": -3,
                      "capInsetsHeight": 1,
                      "capInsetsWidth": 1,
                      "capInsetsX": 0,
                      "capInsetsY": 0,
                      "fileName": null,
                      "fileNameData": {
                        "path": "GUI/image.png",
                        "plistFile": "",
                        "resourceType": 0
                      },
                      "scale9Enable": false,
                      "scale9Height": 80,
                      "scale9Width": 80
                    }
                  },
                  {
                    "classname": "ImageView",
                    "name": null,
                    "children": [],
                    "options": {
                      "__type": "ImageViewSurrogate:#EditorCommon.JsonModel.Component.GUI",
                      "classname": "ImageView",
                      "name": "Image_hero4",
                      "ZOrder": 0,
                      "actiontag": 16657769,
                      "anchorPointX": 0.5,
                      "anchorPointY": 0.5,
                      "classType": "CocoStudio.EngineAdapterWrap.CSImageView",
                      "colorB": 255,
                      "colorG": 255,
                      "colorR": 255,
                      "customProperty": "",
                      "flipX": false,
                      "flipY": false,
                      "height": 80,
                      "ignoreSize": true,
                      "layoutParameter": null,
                      "opacity": 255,
                      "positionPercentX": 2.91538453,
                      "positionPercentY": -0.08571429,
                      "positionType": 0,
                      "rotation": 0,
                      "scaleX": 1,
                      "scaleY": 1,
                      "sizePercentX": 0.615384638,
                      "sizePercentY": 2.28571439,
                      "sizeType": 0,
                      "tag": 144,
                      "touchAble": false,
                      "useMergedTexture": false,
                      "visible": false,
                      "width": 80,
                      "x": 379,
                      "y": -3,
                      "capInsetsHeight": 1,
                      "capInsetsWidth": 1,
                      "capInsetsX": 0,
                      "capInsetsY": 0,
                      "fileName": null,
                      "fileNameData": {
                        "path": "GUI/image.png",
                        "plistFile": "",
                        "resourceType": 0
                      },
                      "scale9Enable": false,
                      "scale9Height": 80,
                      "scale9Width": 80
                    }
                  },
                  {
                    "classname": "ImageView",
                    "name": null,
                    "children": [
                      {
                        "classname": "Label",
                        "name": null,
                        "children": [],
                        "options": {
                          "__type": "LabelSurrogate:#EditorCommon.JsonModel.Component.GUI",
                          "classname": "Label",
                          "name": "Label_master",
                          "ZOrder": 0,
                          "actiontag": 49802017,
                          "anchorPointX": 0.5,
                          "anchorPointY": 0.5,
                          "classType": "CocoStudio.EngineAdapterWrap.CSLabel",
                          "colorB": 17,
                          "colorG": 6,
                          "colorR": 255,
                          "customProperty": "",
                          "flipX": false,
                          "flipY": false,
                          "height": 21,
                          "ignoreSize": true,
                          "layoutParameter": null,
                          "opacity": 255,
                          "positionPercentX": -0.2625,
                          "positionPercentY": 0.3625,
                          "positionType": 0,
                          "rotation": -34.6818733,
                          "scaleX": 1,
                          "scaleY": 1,
                          "sizePercentX": 0.4,
                          "sizePercentY": 0.2625,
                          "sizeType": 0,
                          "tag": 147,
                          "touchAble": false,
                          "useMergedTexture": false,
                          "visible": true,
                          "width": 32,
                          "x": -21,
                          "y": 29,
                          "areaHeight": 0,
                          "areaWidth": 0,
                          "fontFile": null,
                          "fontName": "微软雅黑",
                          "fontSize": 16,
                          "hAlignment": 0,
                          "text": "主将",
                          "touchScaleEnable": false,
                          "vAlignment": 0
                        }
                      }
                    ],
                    "options": {
                      "__type": "ImageViewSurrogate:#EditorCommon.JsonModel.Component.GUI",
                      "classname": "ImageView",
                      "name": "Image_hero5",
                      "ZOrder": 0,
                      "actiontag": 28519191,
                      "anchorPointX": 0.5,
                      "anchorPointY": 0.5,
                      "classType": "CocoStudio.EngineAdapterWrap.CSImageView",
                      "colorB": 255,
                      "colorG": 255,
                      "colorR": 255,
                      "customProperty": "",
                      "flipX": false,
                      "flipY": false,
                      "height": 80,
                      "ignoreSize": true,
                      "layoutParameter": null,
                      "opacity": 255,
                      "positionPercentX": 3.7,
                      "positionPercentY": 0.142857149,
                      "positionType": 0,
                      "rotation": 0,
                      "scaleX": 1.5,
                      "scaleY": 1.5,
                      "sizePercentX": 0.615384638,
                      "sizePercentY": 2.28571439,
                      "sizeType": 0,
                      "tag": 145,
                      "touchAble": false,
                      "useMergedTexture": false,
                      "visible": false,
                      "width": 80,
                      "x": 481,
                      "y": 5,
                      "capInsetsHeight": 1,
                      "capInsetsWidth": 1,
                      "capInsetsX": 0,
                      "capInsetsY": 0,
                      "fileName": null,
                      "fileNameData": {
                        "path": "GUI/image.png",
                        "plistFile": "",
                        "resourceType": 0
                      },
                      "scale9Enable": false,
                      "scale9Height": 80,
                      "scale9Width": 80
                    }
                  }
                ],
                "options": {
                  "__type": "LabelSurrogate:#EditorCommon.JsonModel.Component.GUI",
                  "classname": "Label",
                  "name": "Label_herosText",
                  "ZOrder": 0,
                  "actiontag": 45854602,
                  "anchorPointX": 0.5,
                  "anchorPointY": 0.5,
                  "classType": "CocoStudio.EngineAdapterWrap.CSLabel",
                  "colorB": 255,
                  "colorG": 255,
                  "colorR": 255,
                  "customProperty": "",
                  "flipX": false,
                  "flipY": false,
                  "height": 35,
                  "ignoreSize": true,
                  "layoutParameter": null,
                  "opacity": 255,
                  "positionPercentX": 0.136752144,
                  "positionPercentY": 0.297830373,
                  "positionType": 0,
                  "rotation": 0,
                  "scaleX": 1,
                  "scaleY": 1,
                  "sizePercentX": 0.1388889,
                  "sizePercentY": 0.06903353,
                  "sizeType": 0,
                  "tag": 134,
                  "touchAble": false,
                  "useMergedTexture": false,
                  "visible": true,
                  "width": 130,
                  "x": 128,
                  "y": 151,
                  "areaHeight": 0,
                  "areaWidth": 0,
                  "fontFile": null,
                  "fontName": "微软雅黑",
                  "fontSize": 26,
                  "hAlignment": 0,
                  "text": "敌方武将：",
                  "touchScaleEnable": false,
                  "vAlignment": 0
                }
              },
              {
                "classname": "Label",
                "name": null,
                "children": [
                  {
                    "classname": "ImageView",
                    "name": null,
                    "children": [],
                    "options": {
                      "__type": "ImageViewSurrogate:#EditorCommon.JsonModel.Component.GUI",
                      "classname": "ImageView",
                      "name": "Image_drop1",
                      "ZOrder": 0,
                      "actiontag": 66645523,
                      "anchorPointX": 0.5,
                      "anchorPointY": 0.5,
                      "classType": "CocoStudio.EngineAdapterWrap.CSImageView",
                      "colorB": 255,
                      "colorG": 255,
                      "colorR": 255,
                      "customProperty": "",
                      "flipX": false,
                      "flipY": false,
                      "height": 80,
                      "ignoreSize": true,
                      "layoutParameter": null,
                      "opacity": 255,
                      "positionPercentX": 0.938461542,
                      "positionPercentY": -0.13335833,
                      "positionType": 0,
                      "rotation": 0,
                      "scaleX": 1,
                      "scaleY": 1,
                      "sizePercentX": 0.615384638,
                      "sizePercentY": 2.28571439,
                      "sizeType": 0,
                      "tag": 146,
                      "touchAble": false,
                      "useMergedTexture": false,
                      "visible": false,
                      "width": 80,
                      "x": 122,
                      "y": -4,
                      "capInsetsHeight": 1,
                      "capInsetsWidth": 1,
                      "capInsetsX": 0,
                      "capInsetsY": 0,
                      "fileName": null,
                      "fileNameData": {
                        "path": "GUI/image.png",
                        "plistFile": "",
                        "resourceType": 0
                      },
                      "scale9Enable": false,
                      "scale9Height": 80,
                      "scale9Width": 80
                    }
                  },
                  {
                    "classname": "ImageView",
                    "name": null,
                    "children": [],
                    "options": {
                      "__type": "ImageViewSurrogate:#EditorCommon.JsonModel.Component.GUI",
                      "classname": "ImageView",
                      "name": "Image_drop2",
                      "ZOrder": 0,
                      "actiontag": 52077219,
                      "anchorPointX": 0.5,
                      "anchorPointY": 0.5,
                      "classType": "CocoStudio.EngineAdapterWrap.CSImageView",
                      "colorB": 255,
                      "colorG": 255,
                      "colorR": 255,
                      "customProperty": "",
                      "flipX": false,
                      "flipY": false,
                      "height": 80,
                      "ignoreSize": true,
                      "layoutParameter": null,
                      "opacity": 255,
                      "positionPercentX": 1.66794884,
                      "positionPercentY": -0.13335833,
                      "positionType": 0,
                      "rotation": 0,
                      "scaleX": 1,
                      "scaleY": 1,
                      "sizePercentX": 0.615384638,
                      "sizePercentY": 2.28571439,
                      "sizeType": 0,
                      "tag": 157,
                      "touchAble": false,
                      "useMergedTexture": false,
                      "visible": false,
                      "width": 80,
                      "x": 216,
                      "y": -4,
                      "capInsetsHeight": 1,
                      "capInsetsWidth": 1,
                      "capInsetsX": 0,
                      "capInsetsY": 0,
                      "fileName": null,
                      "fileNameData": {
                        "path": "GUI/image.png",
                        "plistFile": "",
                        "resourceType": 0
                      },
                      "scale9Enable": false,
                      "scale9Height": 80,
                      "scale9Width": 80
                    }
                  },
                  {
                    "classname": "ImageView",
                    "name": null,
                    "children": [],
                    "options": {
                      "__type": "ImageViewSurrogate:#EditorCommon.JsonModel.Component.GUI",
                      "classname": "ImageView",
                      "name": "Image_drop3",
                      "ZOrder": 0,
                      "actiontag": 50533152,
                      "anchorPointX": 0.5,
                      "anchorPointY": 0.5,
                      "classType": "CocoStudio.EngineAdapterWrap.CSImageView",
                      "colorB": 255,
                      "colorG": 255,
                      "colorR": 255,
                      "customProperty": "",
                      "flipX": false,
                      "flipY": false,
                      "height": 80,
                      "ignoreSize": true,
                      "layoutParameter": null,
                      "opacity": 255,
                      "positionPercentX": 2.397436,
                      "positionPercentY": -0.13335833,
                      "positionType": 0,
                      "rotation": 0,
                      "scaleX": 1,
                      "scaleY": 1,
                      "sizePercentX": 0.615384638,
                      "sizePercentY": 2.28571439,
                      "sizeType": 0,
                      "tag": 158,
                      "touchAble": false,
                      "useMergedTexture": false,
                      "visible": false,
                      "width": 80,
                      "x": 311,
                      "y": -4,
                      "capInsetsHeight": 1,
                      "capInsetsWidth": 1,
                      "capInsetsX": 0,
                      "capInsetsY": 0,
                      "fileName": null,
                      "fileNameData": {
                        "path": "GUI/image.png",
                        "plistFile": "",
                        "resourceType": 0
                      },
                      "scale9Enable": false,
                      "scale9Height": 80,
                      "scale9Width": 80
                    }
                  },
                  {
                    "classname": "ImageView",
                    "name": null,
                    "children": [],
                    "options": {
                      "__type": "ImageViewSurrogate:#EditorCommon.JsonModel.Component.GUI",
                      "classname": "ImageView",
                      "name": "Image_drop4",
                      "ZOrder": 0,
                      "actiontag": 33227090,
                      "anchorPointX": 0.5,
                      "anchorPointY": 0.5,
                      "classType": "CocoStudio.EngineAdapterWrap.CSImageView",
                      "colorB": 255,
                      "colorG": 255,
                      "colorR": 255,
                      "customProperty": "",
                      "flipX": false,
                      "flipY": false,
                      "height": 80,
                      "ignoreSize": true,
                      "layoutParameter": null,
                      "opacity": 255,
                      "positionPercentX": 3.12692285,
                      "positionPercentY": -0.13335833,
                      "positionType": 0,
                      "rotation": 0,
                      "scaleX": 1,
                      "scaleY": 1,
                      "sizePercentX": 0.615384638,
                      "sizePercentY": 2.28571439,
                      "sizeType": 0,
                      "tag": 159,
                      "touchAble": false,
                      "useMergedTexture": false,
                      "visible": false,
                      "width": 80,
                      "x": 406,
                      "y": -4,
                      "capInsetsHeight": 1,
                      "capInsetsWidth": 1,
                      "capInsetsX": 0,
                      "capInsetsY": 0,
                      "fileName": null,
                      "fileNameData": {
                        "path": "GUI/image.png",
                        "plistFile": "",
                        "resourceType": 0
                      },
                      "scale9Enable": false,
                      "scale9Height": 80,
                      "scale9Width": 80
                    }
                  }
                ],
                "options": {
                  "__type": "LabelSurrogate:#EditorCommon.JsonModel.Component.GUI",
                  "classname": "Label",
                  "name": "Label_dropText",
                  "ZOrder": 0,
                  "actiontag": 38757337,
                  "anchorPointX": 0.5,
                  "anchorPointY": 0.5,
                  "classType": "CocoStudio.EngineAdapterWrap.CSLabel",
                  "colorB": 255,
                  "colorG": 255,
                  "colorR": 255,
                  "customProperty": "",
                  "flipX": false,
                  "flipY": false,
                  "height": 35,
                  "ignoreSize": true,
                  "layoutParameter": null,
                  "opacity": 255,
                  "positionPercentX": 0.136752144,
                  "positionPercentY": 0.136094674,
                  "positionType": 0,
                  "rotation": 0,
                  "scaleX": 1,
                  "scaleY": 1,
                  "sizePercentX": 0.1388889,
                  "sizePercentY": 0.06903353,
                  "sizeType": 0,
                  "tag": 135,
                  "touchAble": false,
                  "useMergedTexture": false,
                  "visible": true,
                  "width": 130,
                  "x": 128,
                  "y": 69,
                  "areaHeight": 0,
                  "areaWidth": 0,
                  "fontFile": null,
                  "fontName": "微软雅黑",
                  "fontSize": 26,
                  "hAlignment": 0,
                  "text": "征战掉落：",
                  "touchScaleEnable": false,
                  "vAlignment": 0
                }
              },
              {
                "classname": "Button",
                "name": null,
                "children": [],
                "options": {
                  "__type": "ButtonSurrogate:#EditorCommon.JsonModel.Component.GUI",
                  "classname": "Button",
                  "name": "Button_start",
                  "ZOrder": 0,
                  "actiontag": 33000436,
                  "anchorPointX": 0.5,
                  "anchorPointY": 0.5,
                  "classType": "CocoStudio.EngineAdapterWrap.CSButton",
                  "colorB": 255,
                  "colorG": 255,
                  "colorR": 255,
                  "customProperty": "",
                  "flipX": false,
                  "flipY": false,
                  "height": 123,
                  "ignoreSize": true,
                  "layoutParameter": null,
                  "opacity": 255,
                  "positionPercentX": 0.884615362,
                  "positionPercentY": 0.189349115,
                  "positionType": 0,
                  "rotation": 0,
                  "scaleX": 1,
                  "scaleY": 1,
                  "sizePercentX": 0.136752144,
                  "sizePercentY": 0.242603555,
                  "sizeType": 0,
                  "tag": 136,
                  "touchAble": true,
                  "useMergedTexture": false,
                  "visible": true,
                  "width": 128,
                  "x": 828,
                  "y": 96,
                  "capInsetsHeight": 1,
                  "capInsetsWidth": 1,
                  "capInsetsX": 0,
                  "capInsetsY": 0,
                  "disabled": null,
                  "disabledData": {
                    "path": "battlebg/startbtn-disabled.png",
                    "plistFile": "",
                    "resourceType": 0
                  },
                  "fontName": "微软雅黑",
                  "fontSize": 14,
                  "fontType": 0,
                  "normal": null,
                  "normalData": {
                    "path": "battlebg/startbtn.png",
                    "plistFile": "",
                    "resourceType": 0
                  },
                  "pressed": null,
                  "pressedData": {
                    "path": null,
                    "plistFile": null,
                    "resourceType": 0
                  },
                  "scale9Enable": false,
                  "scale9Height": 123,
                  "scale9Width": 128,
                  "text": "",
                  "textColorB": 255,
                  "textColorG": 255,
                  "textColorR": 255
                }
              }
            ],
            "options": {
              "__type": "PanelSurrogate:#EditorCommon.JsonModel.Component.GUI",
              "classname": "Panel",
              "name": "Panel_startBg",
              "ZOrder": 0,
              "actiontag": 2332471,
              "anchorPointX": 0,
              "anchorPointY": 0,
              "classType": "CocoStudio.EngineAdapterWrap.CSPanel",
              "colorB": 255,
              "colorG": 255,
              "colorR": 255,
              "customProperty": "",
              "flipX": false,
              "flipY": false,
              "height": 507,
              "ignoreSize": false,
              "layoutParameter": null,
              "opacity": 255,
              "positionPercentX": 0,
              "positionPercentY": 0,
              "positionType": 0,
              "rotation": 0,
              "scaleX": 1,
              "scaleY": 1,
              "sizePercentX": 1,
              "sizePercentY": 1,
              "sizeType": 0,
              "tag": 124,
              "touchAble": true,
              "useMergedTexture": false,
              "visible": true,
              "width": 936,
              "x": 0,
              "y": 0,
              "adaptScreen": false,
              "backGroundImage": null,
              "backGroundImageData": {
                "path": "battlebg/detail_bg_2.png",
                "plistFile": "",
                "resourceType": 0
              },
              "backGroundScale9Enable": false,
              "bgColorB": 0,
              "bgColorG": 0,
              "bgColorOpacity": 0,
              "bgColorR": 0,
              "bgEndColorB": 255,
              "bgEndColorG": 200,
              "bgEndColorR": 150,
              "bgStartColorB": 255,
              "bgStartColorG": 255,
              "bgStartColorR": 255,
              "capInsetsHeight": 1,
              "capInsetsWidth": 1,
              "capInsetsX": 0,
              "capInsetsY": 0,
              "clipAble": false,
              "colorType": 1,
              "layoutType": 0,
              "vectorX": 0,
              "vectorY": -0.5
            }
          }
        ],
        "options": {
          "__type": "PanelSurrogate:#EditorCommon.JsonModel.Component.GUI",
          "classname": "Panel",
          "name": "Panel_bg",
          "ZOrder": 0,
          "actiontag": 49328407,
          "anchorPointX": 0,
          "anchorPointY": 0,
          "classType": "CocoStudio.EngineAdapterWrap.CSPanel",
          "colorB": 255,
          "colorG": 255,
          "colorR": 255,
          "customProperty": "",
          "flipX": false,
          "flipY": false,
          "height": 507,
          "ignoreSize": false,
          "layoutParameter": {
            "classname": null,
            "name": null,
            "align": 5,
            "gravity": 0,
            "layoutEageType": 0,
            "layoutNormalHorizontal": 0,
            "layoutNormalVertical": 0,
            "layoutParentHorizontal": 0,
            "layoutParentVertical": 0,
            "marginDown": 0,
            "marginLeft": 44,
            "marginRight": 0,
            "marginTop": 130,
            "relativeName": "Panel_bg",
            "relativeToName": "Panel_Root",
            "type": 2
          },
          "opacity": 255,
          "positionPercentX": 0.0125,
          "positionPercentY": 0.103906251,
          "positionType": 0,
          "rotation": 0,
          "scaleX": 1,
          "scaleY": 1,
          "sizePercentX": 0.975,
          "sizePercentY": 0.7921875,
          "sizeType": 0,
          "tag": 6,
          "touchAble": true,
          "useMergedTexture": false,
          "visible": true,
          "width": 936,
          "x": 12,
          "y": 66,
          "adaptScreen": false,
          "backGroundImage": null,
          "backGroundImageData": null,
          "backGroundScale9Enable": false,
          "bgColorB": 255,
          "bgColorG": 200,
          "bgColorOpacity": 0,
          "bgColorR": 150,
          "bgEndColorB": 255,
          "bgEndColorG": 200,
          "bgEndColorR": 150,
          "bgStartColorB": 255,
          "bgStartColorG": 255,
          "bgStartColorR": 255,
          "capInsetsHeight": 1,
          "capInsetsWidth": 1,
          "capInsetsX": 0,
          "capInsetsY": 0,
          "clipAble": false,
          "colorType": 1,
          "layoutType": 0,
          "vectorX": 0,
          "vectorY": -0.5
        }
      },
      {
        "classname": "CheckBox",
        "name": null,
        "children": [],
        "options": {
          "__type": "CheckBoxSurrogate:#EditorCommon.JsonModel.Component.GUI",
          "classname": "CheckBox",
          "name": "stageselect_chapter1",
          "ZOrder": 1,
          "actiontag": 53825900,
          "anchorPointX": 0.5,
          "anchorPointY": 0.5,
          "classType": "CocoStudio.EngineAdapterWrap.CSCheckBox",
          "colorB": 255,
          "colorG": 255,
          "colorR": 255,
          "customProperty": "",
          "flipX": false,
          "flipY": false,
          "height": 32,
          "ignoreSize": true,
          "layoutParameter": {
            "classname": null,
            "name": null,
            "align": 1,
            "gravity": 0,
            "layoutEageType": 0,
            "layoutNormalHorizontal": 0,
            "layoutNormalVertical": 0,
            "layoutParentHorizontal": 0,
            "layoutParentVertical": 0,
            "marginDown": 0,
            "marginLeft": 362,
            "marginRight": 0,
            "marginTop": 511,
            "relativeName": "stageselect_chapter1",
            "relativeToName": "Panel_Root",
            "type": 2
          },
          "opacity": 255,
          "positionPercentX": 0.39375,
          "positionPercentY": 0.1765625,
          "positionType": 0,
          "rotation": 0,
          "scaleX": 0.5,
          "scaleY": 0.5,
          "sizePercentX": 0.0333333351,
          "sizePercentY": 0.05,
          "sizeType": 0,
          "tag": 43,
          "touchAble": false,
          "useMergedTexture": false,
          "visible": true,
          "width": 32,
          "x": 378,
          "y": 113,
          "backGroundBox": null,
          "backGroundBoxData": {
            "path": "stageselect_chapter_dot.png",
            "plistFile": "",
            "resourceType": 0
          },
          "backGroundBoxDisabled": null,
          "backGroundBoxDisabledData": {
            "path": null,
            "plistFile": null,
            "resourceType": 0
          },
          "backGroundBoxSelected": null,
          "backGroundBoxSelectedData": {
            "path": null,
            "plistFile": null,
            "resourceType": 0
          },
          "frontCross": null,
          "frontCrossData": {
            "path": "stageselect_chapter_cursor.png",
            "plistFile": "",
            "resourceType": 0
          },
          "frontCrossDisabled": null,
          "frontCrossDisabledData": {
            "path": "stageselect_chapter_dot.png",
            "plistFile": "",
            "resourceType": 0
          },
          "selectedState": false
        }
      }
    ],
    "options": {
      "__type": "PanelSurrogate:#EditorCommon.JsonModel.Component.GUI",
      "classname": "Panel",
      "name": "Panel_Root",
      "ZOrder": 0,
      "actiontag": -1,
      "anchorPointX": 0,
      "anchorPointY": 0,
      "classType": "CocoStudio.EngineAdapterWrap.CSPanel",
      "colorB": 255,
      "colorG": 255,
      "colorR": 255,
      "customProperty": "",
      "flipX": false,
      "flipY": false,
      "height": 640,
      "ignoreSize": false,
      "layoutParameter": null,
      "opacity": 255,
      "positionPercentX": 0,
      "positionPercentY": 0,
      "positionType": 0,
      "rotation": 0,
      "scaleX": 1,
      "scaleY": 1,
      "sizePercentX": 1,
      "sizePercentY": 1,
      "sizeType": 0,
      "tag": 3,
      "touchAble": true,
      "useMergedTexture": false,
      "visible": true,
      "width": 960,
      "x": 0,
      "y": 0,
      "adaptScreen": true,
      "backGroundImage": null,
      "backGroundImageData": null,
      "backGroundScale9Enable": false,
      "bgColorB": 255,
      "bgColorG": 200,
      "bgColorOpacity": 0,
      "bgColorR": 150,
      "bgEndColorB": 255,
      "bgEndColorG": 200,
      "bgEndColorR": 150,
      "bgStartColorB": 255,
      "bgStartColorG": 255,
      "bgStartColorR": 255,
      "capInsetsHeight": 1,
      "capInsetsWidth": 1,
      "capInsetsX": 0,
      "capInsetsY": 0,
      "clipAble": false,
      "colorType": 1,
      "layoutType": 3,
      "vectorX": 0,
      "vectorY": -0.5
    }
  }
}